[
  {
    "inputs": [
      {
        "internalType": "string",
        "name": "name",
        "type": "string"
      },
      {
        "internalType": "string",
        "name": "symbol",
        "type": "string"
      },
      {
        "internalType": "uint256",
        "name": "_initialSupply",
        "type": "uint256"
      },
      {
        "internalType": "uint256",
        "name": "_maxSupply",
        "type": "uint256"
      },
      {
        "internalType": "uint256",
        "name": "_initialPrice",
        "type": "uint256"
      },
      {
        "internalType": "address",
        "name": "_creator",
        "type": "address"
      },
      {
        "internalType": "uint256",
        "name": "_creatorLockupPeriod",
        "type": "uint256"
      },
      {
        "internalType": "address",
        "name": "_factory",
        "type": "address"
      }
    ],
    "stateMutability": "nonpayable",
    "type": "constructor"
  },
  {
    "inputs": [
      {
        "internalType": "address",
        "name": "spender",
        "type": "address"
      },
      {
        "internalType": "uint256",
        "name": "allowance",
        "type": "uint256"
      },
      {
        "internalType": "uint256",
        "name": "needed",
        "type": "uint256"
      }
    ],
    "name": "ERC20InsufficientAllowance",
    "type": "error"
  },
  {
    "inputs": [
      {
        "internalType": "address",
        "name": "sender",
        "type": "address"
      },
      {
        "internalType": "uint256",
        "name": "balance",
        "type": "uint256"
      },
      {
        "internalType": "uint256",
        "name": "needed",
        "type": "uint256"
      }
    ],
    "name": "ERC20InsufficientBalance",
    "type": "error"
  },
  {
    "inputs": [
      {
        "internalType": "address",
        "name": "approver",
        "type": "address"
      }
    ],
    "name": "ERC20InvalidApprover",
    "type": "error"
  },
  {
    "inputs": [
      {
        "internalType": "address",
        "name": "receiver",
        "type": "address"
      }
    ],
    "name": "ERC20InvalidReceiver",
    "type": "error"
  },
  {
    "inputs": [
      {
        "internalType": "address",
        "name": "sender",
        "type": "address"
      }
    ],
    "name": "ERC20InvalidSender",
    "type": "error"
  },
  {
    "inputs": [
      {
        "internalType": "address",
        "name": "spender",
        "type": "address"
      }
    ],
    "name": "ERC20InvalidSpender",
    "type": "error"
  },
  {
    "anonymous": false,
    "inputs": [
      {
        "indexed": true,
        "internalType": "address",
        "name": "owner",
        "type": "address"
      },
      {
        "indexed": true,
        "internalType": "address",
        "name": "spender",
        "type": "address"
      },
      {
        "indexed": false,
        "internalType": "uint256",
        "name": "value",
        "type": "uint256"
      }
    ],
    "name": "Approval",
    "type": "event"
  },
  {
    "anonymous": false,
    "inputs": [
      {
        "indexed": false,
        "internalType": "bool",
        "name": "enabled",
        "type": "bool"
      }
    ],
    "name": "BondingCurveStatusChanged",
    "type": "event"
  },
  {
    "anonymous": false,
    "inputs": [
      {
        "indexed": false,
        "internalType": "uint256",
        "name": "timestamp",
        "type": "uint256"
      },
      {
        "indexed": false,
        "internalType": "uint256",
        "name": "open",
        "type": "uint256"
      },
      {
        "indexed": false,
        "internalType": "uint256",
        "name": "high",
        "type": "uint256"
      },
      {
        "indexed": false,
        "internalType": "uint256",
        "name": "low",
        "type": "uint256"
      },
      {
        "indexed": false,
        "internalType": "uint256",
        "name": "close",
        "type": "uint256"
      },
      {
        "indexed": false,
        "internalType": "uint256",
        "name": "volume",
        "type": "uint256"
      }
    ],
    "name": "CandleUpdated",
    "type": "event"
  },
  {
    "anonymous": false,
    "inputs": [
      {
        "indexed": true,
        "internalType": "address",
        "name": "holder",
        "type": "address"
      },
      {
        "indexed": false,
        "internalType": "uint256",
        "name": "unlockTime",
        "type": "uint256"
      }
    ],
    "name": "HolderLocked",
    "type": "event"
  },
  {
    "anonymous": false,
    "inputs": [
      {
        "indexed": false,
        "internalType": "uint256",
        "name": "newPrice",
        "type": "uint256"
      },
      {
        "indexed": false,
        "internalType": "uint256",
        "name": "marketCap",
        "type": "uint256"
      }
    ],
    "name": "PriceUpdate",
    "type": "event"
  },
  {
    "anonymous": false,
    "inputs": [
      {
        "indexed": true,
        "internalType": "address",
        "name": "buyer",
        "type": "address"
      },
      {
        "indexed": false,
        "internalType": "uint256",
        "name": "amountPaid",
        "type": "uint256"
      },
      {
        "indexed": false,
        "internalType": "uint256",
        "name": "tokensMinted",
        "type": "uint256"
      },
      {
        "indexed": false,
        "internalType": "uint256",
        "name": "price",
        "type": "uint256"
      }
    ],
    "name": "TokensPurchased",
    "type": "event"
  },
  {
    "anonymous": false,
    "inputs": [
      {
        "indexed": true,
        "internalType": "address",
        "name": "seller",
        "type": "address"
      },
      {
        "indexed": false,
        "internalType": "uint256",
        "name": "amountReceived",
        "type": "uint256"
      },
      {
        "indexed": false,
        "internalType": "uint256",
        "name": "tokensBurned",
        "type": "uint256"
      },
      {
        "indexed": false,
        "internalType": "uint256",
        "name": "price",
        "type": "uint256"
      }
    ],
    "name": "TokensSold",
    "type": "event"
  },
  {
    "anonymous": false,
    "inputs": [
      {
        "indexed": false,
        "internalType": "address",
        "name": "holder",
        "type": "address"
      },
      {
        "indexed": false,
        "internalType": "uint256",
        "name": "balance",
        "type": "uint256"
      },
      {
        "indexed": false,
        "internalType": "uint256",
        "name": "percentage",
        "type": "uint256"
      }
    ],
    "name": "TopHolderAdded",
    "type": "event"
  },
  {
    "anonymous": false,
    "inputs": [
      {
        "indexed": false,
        "internalType": "address",
        "name": "holder",
        "type": "address"
      }
    ],
    "name": "TopHolderRemoved",
    "type": "event"
  },
  {
    "anonymous": false,
    "inputs": [
      {
        "indexed": false,
        "internalType": "bool",
        "name": "enabled",
        "type": "bool"
      }
    ],
    "name": "TradingStatusChanged",
    "type": "event"
  },
  {
    "anonymous": false,
    "inputs": [
      {
        "indexed": true,
        "internalType": "address",
        "name": "from",
        "type": "address"
      },
      {
        "indexed": true,
        "internalType": "address",
        "name": "to",
        "type": "address"
      },
      {
        "indexed": false,
        "internalType": "uint256",
        "name": "value",
        "type": "uint256"
      }
    ],
    "name": "Transfer",
    "type": "event"
  },
  {
    "inputs": [],
    "name": "LARGE_HOLDER_LOCK_PERIOD",
    "outputs": [
      {
        "internalType": "uint256",
        "name": "",
        "type": "uint256"
      }
    ],
    "stateMutability": "view",
    "type": "function"
  },
  {
    "inputs": [],
    "name": "LARGE_HOLDER_THRESHOLD",
    "outputs": [
      {
        "internalType": "uint256",
        "name": "",
        "type": "uint256"
      }
    ],
    "stateMutability": "view",
    "type": "function"
  },
  {
    "inputs": [],
    "name": "MAX_RECENT_TRANSACTIONS",
    "outputs": [
      {
        "internalType": "uint256",
        "name": "",
        "type": "uint256"
      }
    ],
    "stateMutability": "view",
    "type": "function"
  },
  {
    "inputs": [],
    "name": "MAX_TOP_HOLDERS",
    "outputs": [
      {
        "internalType": "uint256",
        "name": "",
        "type": "uint256"
      }
    ],
    "stateMutability": "view",
    "type": "function"
  },
  {
    "inputs": [],
    "name": "PRICE_INCREASE_PERCENT",
    "outputs": [
      {
        "internalType": "uint256",
        "name": "",
        "type": "uint256"
      }
    ],
    "stateMutability": "view",
    "type": "function"
  },
  {
    "inputs": [],
    "name": "STEP_SIZE",
    "outputs": [
      {
        "internalType": "uint256",
        "name": "",
        "type": "uint256"
      }
    ],
    "stateMutability": "view",
    "type": "function"
  },
  {
    "inputs": [
      {
        "internalType": "address",
        "name": "owner",
        "type": "address"
      },
      {
        "internalType": "address",
        "name": "spender",
        "type": "address"
      }
    ],
    "name": "allowance",
    "outputs": [
      {
        "internalType": "uint256",
        "name": "",
        "type": "uint256"
      }
    ],
    "stateMutability": "view",
    "type": "function"
  },
  {
    "inputs": [
      {
        "internalType": "address",
        "name": "spender",
        "type": "address"
      },
      {
        "internalType": "uint256",
        "name": "value",
        "type": "uint256"
      }
    ],
    "name": "approve",
    "outputs": [
      {
        "internalType": "bool",
        "name": "",
        "type": "bool"
      }
    ],
    "stateMutability": "nonpayable",
    "type": "function"
  },
  {
    "inputs": [
      {
        "internalType": "address",
        "name": "account",
        "type": "address"
      }
    ],
    "name": "balanceOf",
    "outputs": [
      {
        "internalType": "uint256",
        "name": "",
        "type": "uint256"
      }
    ],
    "stateMutability": "view",
    "type": "function"
  },
  {
    "inputs": [],
    "name": "bondingCurveEnabled",
    "outputs": [
      {
        "internalType": "bool",
        "name": "",
        "type": "bool"
      }
    ],
    "stateMutability": "view",
    "type": "function"
  },
  {
    "inputs": [
      {
        "internalType": "uint256",
        "name": "value",
        "type": "uint256"
      }
    ],
    "name": "burn",
    "outputs": [],
    "stateMutability": "nonpayable",
    "type": "function"
  },
  {
    "inputs": [
      {
        "internalType": "address",
        "name": "account",
        "type": "address"
      },
      {
        "internalType": "uint256",
        "name": "value",
        "type": "uint256"
      }
    ],
    "name": "burnFrom",
    "outputs": [],
    "stateMutability": "nonpayable",
    "type": "function"
  },
  {
    "inputs": [
      {
        "internalType": "uint256",
        "name": "desiredTokenAmount",
        "type": "uint256"
      }
    ],
    "name": "buyTokens",
    "outputs": [
      {
        "internalType": "uint256",
        "name": "actualTokenAmount",
        "type": "uint256"
      }
    ],
    "stateMutability": "payable",
    "type": "function"
  },
  {
    "inputs": [],
    "name": "buyTokensWithEth",
    "outputs": [
      {
        "internalType": "uint256",
        "name": "tokenAmount",
        "type": "uint256"
      }
    ],
    "stateMutability": "payable",
    "type": "function"
  },
  {
    "inputs": [
      {
        "internalType": "uint256",
        "name": "tokenAmount",
        "type": "uint256"
      }
    ],
    "name": "calculatePurchasePrice",
    "outputs": [
      {
        "internalType": "uint256",
        "name": "",
        "type": "uint256"
      }
    ],
    "stateMutability": "view",
    "type": "function"
  },
  {
    "inputs": [
      {
        "internalType": "uint256",
        "name": "ethAmount",
        "type": "uint256"
      }
    ],
    "name": "calculatePurchaseReturn",
    "outputs": [
      {
        "internalType": "uint256",
        "name": "",
        "type": "uint256"
      }
    ],
    "stateMutability": "view",
    "type": "function"
  },
  {
    "inputs": [
      {
        "internalType": "uint256",
        "name": "tokenAmount",
        "type": "uint256"
      }
    ],
    "name": "calculateSaleReturn",
    "outputs": [
      {
        "internalType": "uint256",
        "name": "",
        "type": "uint256"
      }
    ],
    "stateMutability": "view",
    "type": "function"
  },
  {
    "inputs": [
      {
        "internalType": "uint256",
        "name": "",
        "type": "uint256"
      }
    ],
    "name": "candleTimestamps",
    "outputs": [
      {
        "internalType": "uint256",
        "name": "",
        "type": "uint256"
      }
    ],
    "stateMutability": "view",
    "type": "function"
  },
  {
    "inputs": [],
    "name": "creator",
    "outputs": [
      {
        "internalType": "address",
        "name": "",
        "type": "address"
      }
    ],
    "stateMutability": "view",
    "type": "function"
  },
  {
    "inputs": [],
    "name": "creatorLockupEnds",
    "outputs": [
      {
        "internalType": "uint256",
        "name": "",
        "type": "uint256"
      }
    ],
    "stateMutability": "view",
    "type": "function"
  },
  {
    "inputs": [],
    "name": "creatorLockupPeriod",
    "outputs": [
      {
        "internalType": "uint256",
        "name": "",
        "type": "uint256"
      }
    ],
    "stateMutability": "view",
    "type": "function"
  },
  {
    "inputs": [],
    "name": "currentPrice",
    "outputs": [
      {
        "internalType": "uint256",
        "name": "",
        "type": "uint256"
      }
    ],
    "stateMutability": "view",
    "type": "function"
  },
  {
    "inputs": [],
    "name": "decimals",
    "outputs": [
      {
        "internalType": "uint8",
        "name": "",
        "type": "uint8"
      }
    ],
    "stateMutability": "view",
    "type": "function"
  },
  {
    "inputs": [],
    "name": "factory",
    "outputs": [
      {
        "internalType": "address",
        "name": "",
        "type": "address"
      }
    ],
    "stateMutability": "view",
    "type": "function"
  },
  {
    "inputs": [
      {
        "internalType": "uint256",
        "name": "count",
        "type": "uint256"
      }
    ],
    "name": "getCandleData",
    "outputs": [
      {
        "internalType": "uint256[]",
        "name": "timestamps",
        "type": "uint256[]"
      },
      {
        "internalType": "uint256[]",
        "name": "opens",
        "type": "uint256[]"
      },
      {
        "internalType": "uint256[]",
        "name": "highs",
        "type": "uint256[]"
      },
      {
        "internalType": "uint256[]",
        "name": "lows",
        "type": "uint256[]"
      },
      {
        "internalType": "uint256[]",
        "name": "closes",
        "type": "uint256[]"
      },
      {
        "internalType": "uint256[]",
        "name": "volumes",
        "type": "uint256[]"
      }
    ],
    "stateMutability": "view",
    "type": "function"
  },
  {
    "inputs": [],
    "name": "getCurrentPrice",
    "outputs": [
      {
        "internalType": "uint256",
        "name": "",
        "type": "uint256"
      }
    ],
    "stateMutability": "view",
    "type": "function"
  },
  {
    "inputs": [
      {
        "internalType": "address",
        "name": "holder",
        "type": "address"
      }
    ],
    "name": "getHolderUnlockTime",
    "outputs": [
      {
        "internalType": "uint256",
        "name": "",
        "type": "uint256"
      }
    ],
    "stateMutability": "view",
    "type": "function"
  },
  {
    "inputs": [
      {
        "internalType": "uint256",
        "name": "count",
        "type": "uint256"
      }
    ],
    "name": "getRecentTransactions",
    "outputs": [
      {
        "internalType": "address[]",
        "name": "accounts",
        "type": "address[]"
      },
      {
        "internalType": "bool[]",
        "name": "isBuys",
        "type": "bool[]"
      },
      {
        "internalType": "uint256[]",
        "name": "tokenAmounts",
        "type": "uint256[]"
      },
      {
        "internalType": "uint256[]",
        "name": "ethAmounts",
        "type": "uint256[]"
      },
      {
        "internalType": "uint256[]",
        "name": "prices",
        "type": "uint256[]"
      },
      {
        "internalType": "uint256[]",
        "name": "timestamps",
        "type": "uint256[]"
      }
    ],
    "stateMutability": "view",
    "type": "function"
  },
  {
    "inputs": [],
    "name": "getReserveBalance",
    "outputs": [
      {
        "internalType": "uint256",
        "name": "",
        "type": "uint256"
      }
    ],
    "stateMutability": "view",
    "type": "function"
  },
  {
    "inputs": [],
    "name": "getTokenStatistics",
    "outputs": [
      {
        "internalType": "uint256",
        "name": "currentTokenPrice",
        "type": "uint256"
      },
      {
        "internalType": "uint256",
        "name": "currentMarketCap",
        "type": "uint256"
      },
      {
        "internalType": "uint256",
        "name": "volumeTraded",
        "type": "uint256"
      },
      {
        "internalType": "uint256",
        "name": "ath",
        "type": "uint256"
      },
      {
        "internalType": "uint256",
        "name": "atl",
        "type": "uint256"
      }
    ],
    "stateMutability": "view",
    "type": "function"
  },
  {
    "inputs": [],
    "name": "getTopHolders",
    "outputs": [
      {
        "internalType": "address[]",
        "name": "holders",
        "type": "address[]"
      },
      {
        "internalType": "uint256[]",
        "name": "balances",
        "type": "uint256[]"
      },
      {
        "internalType": "uint256[]",
        "name": "percentages",
        "type": "uint256[]"
      }
    ],
    "stateMutability": "view",
    "type": "function"
  },
  {
    "inputs": [],
    "name": "highestPrice",
    "outputs": [
      {
        "internalType": "uint256",
        "name": "",
        "type": "uint256"
      }
    ],
    "stateMutability": "view",
    "type": "function"
  },
  {
    "inputs": [
      {
        "internalType": "address",
        "name": "",
        "type": "address"
      }
    ],
    "name": "holderLockTime",
    "outputs": [
      {
        "internalType": "uint256",
        "name": "",
        "type": "uint256"
      }
    ],
    "stateMutability": "view",
    "type": "function"
  },
  {
    "inputs": [
      {
        "internalType": "uint256",
        "name": "",
        "type": "uint256"
      }
    ],
    "name": "hourlyCandles",
    "outputs": [
      {
        "internalType": "uint256",
        "name": "timestamp",
        "type": "uint256"
      },
      {
        "internalType": "uint256",
        "name": "open",
        "type": "uint256"
      },
      {
        "internalType": "uint256",
        "name": "high",
        "type": "uint256"
      },
      {
        "internalType": "uint256",
        "name": "low",
        "type": "uint256"
      },
      {
        "internalType": "uint256",
        "name": "close",
        "type": "uint256"
      },
      {
        "internalType": "uint256",
        "name": "volume",
        "type": "uint256"
      }
    ],
    "stateMutability": "view",
    "type": "function"
  },
  {
    "inputs": [],
    "name": "initialPrice",
    "outputs": [
      {
        "internalType": "uint256",
        "name": "",
        "type": "uint256"
      }
    ],
    "stateMutability": "view",
    "type": "function"
  },
  {
    "inputs": [],
    "name": "initialSupply",
    "outputs": [
      {
        "internalType": "uint256",
        "name": "",
        "type": "uint256"
      }
    ],
    "stateMutability": "view",
    "type": "function"
  },
  {
    "inputs": [
      {
        "internalType": "address",
        "name": "holder",
        "type": "address"
      }
    ],
    "name": "isHolderLocked",
    "outputs": [
      {
        "internalType": "bool",
        "name": "",
        "type": "bool"
      }
    ],
    "stateMutability": "view",
    "type": "function"
  },
  {
    "inputs": [
      {
        "internalType": "address",
        "name": "",
        "type": "address"
      }
    ],
    "name": "isTopHolder",
    "outputs": [
      {
        "internalType": "bool",
        "name": "",
        "type": "bool"
      }
    ],
    "stateMutability": "view",
    "type": "function"
  },
  {
    "inputs": [],
    "name": "lowestPrice",
    "outputs": [
      {
        "internalType": "uint256",
        "name": "",
        "type": "uint256"
      }
    ],
    "stateMutability": "view",
    "type": "function"
  },
  {
    "inputs": [],
    "name": "marketCap",
    "outputs": [
      {
        "internalType": "uint256",
        "name": "",
        "type": "uint256"
      }
    ],
    "stateMutability": "view",
    "type": "function"
  },
  {
    "inputs": [],
    "name": "maxSupply",
    "outputs": [
      {
        "internalType": "uint256",
        "name": "",
        "type": "uint256"
      }
    ],
    "stateMutability": "view",
    "type": "function"
  },
  {
    "inputs": [],
    "name": "name",
    "outputs": [
      {
        "internalType": "string",
        "name": "",
        "type": "string"
      }
    ],
    "stateMutability": "view",
    "type": "function"
  },
  {
    "inputs": [
      {
        "internalType": "uint256",
        "name": "",
        "type": "uint256"
      }
    ],
    "name": "recentTransactions",
    "outputs": [
      {
        "internalType": "address",
        "name": "account",
        "type": "address"
      },
      {
        "internalType": "bool",
        "name": "isBuy",
        "type": "bool"
      },
      {
        "internalType": "uint256",
        "name": "tokenAmount",
        "type": "uint256"
      },
      {
        "internalType": "uint256",
        "name": "ethAmount",
        "type": "uint256"
      },
      {
        "internalType": "uint256",
        "name": "price",
        "type": "uint256"
      },
      {
        "internalType": "uint256",
        "name": "timestamp",
        "type": "uint256"
      }
    ],
    "stateMutability": "view",
    "type": "function"
  },
  {
    "inputs": [],
    "name": "reserveBalance",
    "outputs": [
      {
        "internalType": "uint256",
        "name": "",
        "type": "uint256"
      }
    ],
    "stateMutability": "view",
    "type": "function"
  },
  {
    "inputs": [
      {
        "internalType": "uint256",
        "name": "tokenAmount",
        "type": "uint256"
      }
    ],
    "name": "sellTokens",
    "outputs": [
      {
        "internalType": "uint256",
        "name": "ethReceived",
        "type": "uint256"
      }
    ],
    "stateMutability": "nonpayable",
    "type": "function"
  },
  {
    "inputs": [
      {
        "internalType": "bool",
        "name": "enabled",
        "type": "bool"
      }
    ],
    "name": "setBondingCurveEnabled",
    "outputs": [],
    "stateMutability": "nonpayable",
    "type": "function"
  },
  {
    "inputs": [
      {
        "internalType": "bool",
        "name": "enabled",
        "type": "bool"
      }
    ],
    "name": "setTradingEnabled",
    "outputs": [],
    "stateMutability": "nonpayable",
    "type": "function"
  },
  {
    "inputs": [],
    "name": "symbol",
    "outputs": [
      {
        "internalType": "string",
        "name": "",
        "type": "string"
      }
    ],
    "stateMutability": "view",
    "type": "function"
  },
  {
    "inputs": [
      {
        "internalType": "uint256",
        "name": "",
        "type": "uint256"
      }
    ],
    "name": "topHolders",
    "outputs": [
      {
        "internalType": "address",
        "name": "",
        "type": "address"
      }
    ],
    "stateMutability": "view",
    "type": "function"
  },
  {
    "inputs": [],
    "name": "totalSupply",
    "outputs": [
      {
        "internalType": "uint256",
        "name": "",
        "type": "uint256"
      }
    ],
    "stateMutability": "view",
    "type": "function"
  },
  {
    "inputs": [],
    "name": "totalVolume",
    "outputs": [
      {
        "internalType": "uint256",
        "name": "",
        "type": "uint256"
      }
    ],
    "stateMutability": "view",
    "type": "function"
  },
  {
    "inputs": [],
    "name": "tradingEnabled",
    "outputs": [
      {
        "internalType": "bool",
        "name": "",
        "type": "bool"
      }
    ],
    "stateMutability": "view",
    "type": "function"
  },
  {
    "inputs": [
      {
        "internalType": "address",
        "name": "to",
        "type": "address"
      },
      {
        "internalType": "uint256",
        "name": "value",
        "type": "uint256"
      }
    ],
    "name": "transfer",
    "outputs": [
      {
        "internalType": "bool",
        "name": "",
        "type": "bool"
      }
    ],
    "stateMutability": "nonpayable",
    "type": "function"
  },
  {
    "inputs": [
      {
        "internalType": "address",
        "name": "from",
        "type": "address"
      },
      {
        "internalType": "address",
        "name": "to",
        "type": "address"
      },
      {
        "internalType": "uint256",
        "name": "value",
        "type": "uint256"
      }
    ],
    "name": "transferFrom",
    "outputs": [
      {
        "internalType": "bool",
        "name": "",
        "type": "bool"
      }
    ],
    "stateMutability": "nonpayable",
    "type": "function"
  },
  {
    "stateMutability": "payable",
    "type": "receive"
  }
]
